{
  "afosdick":{"file":"afosdick.json","name":"Alex Fosdick"},
  "smhicks":{"file":"smhicks.json","name":"Sean Hicks"},
  "diol1907":{"file":"diol1907.json","name":"Diana Southard"},
  "aaba2758":{"file":"aaba2758.json","name":"Aaresh R Bachana"},
  "swaminath":{"file":"swba6009.json","name":"Swaminath Badrinath"},
  "nathangustilo":{"file":"nagu6084.json","name":"Nathan Gustilo"},
  "hash5422":{"file":"hash5422.json","name":"Harshil A. Sheth"},
  "abma3731":{"file":"abma3731.json","name":"Abhilash Manjunath"},
  "iskh3297":{"file":"iskh3297.json","name":"Isaac Khader"},
  "such2660":{"file":"such2660.json","name":"Suraj Sridhar"},
  "aava6580":{"file":"aava6580.json","name":"Aayushi Vatsyayan"},
  "issh3874":{"file":"issh3874.json","name":"Ishan Shah"}
}

